sqlmodel_v2_beta/__init__.py
sqlmodel_v2_beta/default.py
sqlmodel_v2_beta/engine/__init__.py
sqlmodel_v2_beta/engine/create.py
sqlmodel_v2_beta/engine/result.py
sqlmodel_v2_beta/ext/__init__.py
sqlmodel_v2_beta/ext/asyncio/__init__.py
sqlmodel_v2_beta/ext/asyncio/session.py
sqlmodel_v2_beta/main.py
sqlmodel_v2_beta/orm/__init__.py
sqlmodel_v2_beta/orm/session.py
sqlmodel_v2_beta/pool/__init__.py
sqlmodel_v2_beta/py.typed
sqlmodel_v2_beta/sql/__init__.py
sqlmodel_v2_beta/sql/base.py
sqlmodel_v2_beta/sql/expression.py
sqlmodel_v2_beta/sql/expression.py.jinja2
sqlmodel_v2_beta/sql/sqltypes.py
sqlmodel_v2_beta/typing.py
sqlmodel_v2_beta-0.0.11.dist-info/LICENSE
sqlmodel_v2_beta-0.0.11.dist-info/METADATA
sqlmodel_v2_beta-0.0.11.dist-info/WHEEL
sqlmodel_v2_beta-0.0.11.dist-info/RECORD
