Metadata-Version: 2.1
Name: sqlmodel-v2-beta
Version: 0.0.11
Summary: SQLModel, SQL databases in Python, designed for simplicity, compatibility, and robustness.
Home-page: https://github.com/tiangolo/sqlmodel
License: MIT
Author: Sebastián Ramírez
Author-email: tiangolo@gmail.com
Requires-Python: >=3.7,<4.0
Classifier: Development Status :: 4 - Beta
Classifier: Framework :: AsyncIO
Classifier: Intended Audience :: Developers
Classifier: Intended Audience :: Science/Research
Classifier: Intended Audience :: System Administrators
Classifier: License :: OSI Approved :: MIT License
Classifier: Programming Language :: Python :: 3
Classifier: Programming Language :: Python :: 3.7
Classifier: Programming Language :: Python :: 3.8
Classifier: Programming Language :: Python :: 3.9
Classifier: Programming Language :: Python :: 3.10
Classifier: Programming Language :: Python :: 3.11
Classifier: Programming Language :: Python :: 3 :: Only
Classifier: Topic :: Database
Classifier: Topic :: Database :: Database Engines/Servers
Classifier: Topic :: Internet
Classifier: Topic :: Internet :: WWW/HTTP
Classifier: Topic :: Internet :: WWW/HTTP :: HTTP Servers
Classifier: Typing :: Typed
Requires-Dist: SQLAlchemy (>=2.0.0,<=2.0.22)
Requires-Dist: pydantic[email] (>=2.1.1,<=2.4.2)
Project-URL: Documentation, https://sqlmodel.tiangolo.com
Project-URL: Repository, https://github.com/gcandau/sqlmodel
